bagcheck/__init__.py
bagcheck/bagcheck.py
bagcheck/concourse/checks.py
bagcheck/concourse/cli.py
bagcheck/concourse/jobs.py
bagcheck/concourse/pipeline.py
bagcheck/concourse/resources.py
bagcheck/concourse/step.py
bagcheck/concourse/summary.py
bagcheck/concourse/task.py
bagcheck/github/checks.py
bagcheck/github/cli.py
bagcheck/github/constants.py
bagcheck/github/summary.py
bagcheck/github/triggers.py
bagcheck/github/utils.py
bagcheck/github/workflow.py
bagcheck/luggage.py
bagcheck/utils.py
bagcheck-0.2.13.dist-info/LICENSE
bagcheck-0.2.13.dist-info/METADATA
bagcheck-0.2.13.dist-info/WHEEL
bagcheck-0.2.13.dist-info/entry_points.txt
bagcheck-0.2.13.dist-info/RECORD
