Metadata-Version: 2.1
Name: bagcheck
Version: 0.2.13
Summary: A pipeline validation tool for Concourse and GitHub Actions
Home-page: https://github.com/jfcarter2358/bagcheck
License: MIT
Keywords: concourse,github-actions,bagcheck
Author: John Carter
Author-email: jfcarter2358@gmail.com
Requires-Python: >=3.10,<4.0
Classifier: License :: OSI Approved :: MIT License
Classifier: Programming Language :: Python :: 3
Classifier: Programming Language :: Python :: 3.10
Classifier: Programming Language :: Python :: 3.11
Classifier: Programming Language :: Python :: 3.12
Classifier: Programming Language :: Python :: 3.13
Requires-Dist: jsonpath-ng (>=1.5.3,<2.0.0)
Requires-Dist: pyyaml (>=6.0,<7.0)
Requires-Dist: requests (>=2.32.4,<3.0.0)
Requires-Dist: rich-click (>=1.5.2,<2.0.0)
Project-URL: Repository, https://github.com/jfcarter2358/bagcheck
